mqt_ion_shuttler-0.1.dist-info/licenses/LICENSE
multi_shuttler/__init__.py
multi_shuttler/Inside/__init__.py
multi_shuttler/Inside/compilation.py
multi_shuttler/Inside/cycles.py
multi_shuttler/Inside/graph_utils.py
multi_shuttler/Inside/partition.py
multi_shuttler/Inside/paths.py
multi_shuttler/Inside/plotting.py
multi_shuttler/Inside/run.py
multi_shuttler/Inside/scheduling.py
multi_shuttler/Inside/shuttle.py
multi_shuttler/Outside/__init__.py
multi_shuttler/Outside/compilation.py
multi_shuttler/Outside/cycles.py
multi_shuttler/Outside/graph_utils.py
multi_shuttler/Outside/partition.py
multi_shuttler/Outside/paths.py
multi_shuttler/Outside/plotting.py
multi_shuttler/Outside/scheduling.py
multi_shuttler/Outside/shuttle.py
single_shuttler/SAT.py
single_shuttler/__init__.py
single_shuttler/compilation.py
single_shuttler/cycles.py
single_shuttler/graph_utils.py
single_shuttler/plotting.py
single_shuttler/run.py
single_shuttler/run_benchmarks.py
single_shuttler/run_heuristic.py
single_shuttler/scheduling.py
mqt_ion_shuttler-0.1.dist-info/METADATA
mqt_ion_shuttler-0.1.dist-info/WHEEL
mqt_ion_shuttler-0.1.dist-info/top_level.txt
mqt_ion_shuttler-0.1.dist-info/RECORD
