Metadata-Version: 2.4
Name: mqt-ion-shuttler
Version: 0.1
Summary: A solver for the shuttling problem in QCCD quantum computers
Author-email: Daniel Schoenberger <daniel.schoenberger@tum.de>
License: MIT License
Keywords: MQT,quantum computing,compilation,shuttling,design automation,sat solver
Requires-Python: >=3.8
License-File: LICENSE
Requires-Dist: z3-solver==4.12.1.0
Requires-Dist: matplotlib==3.7.1
Requires-Dist: networkx==3.0
Requires-Dist: qiskit==1.0.0
Requires-Dist: more_itertools==10.1.0
Dynamic: license-file
